RFXtrx/__init__.py
RFXtrx/lowlevel.py
pyrfxtrx-0.32.0.dist-info/licenses/COPYING.txt
pyrfxtrx-0.32.0.dist-info/METADATA
pyrfxtrx-0.32.0.dist-info/WHEEL
pyrfxtrx-0.32.0.dist-info/top_level.txt
pyrfxtrx-0.32.0.dist-info/RECORD
